aind_ants_transform_sidecar/__init__.py
aind_ants_transform_sidecar/py.typed
aind_ants_transform_sidecar/sidecar.py
aind_ants_transform_sidecar/scripts/__init__.py
aind_ants_transform_sidecar-0.1.0.dist-info/licenses/LICENSE
aind_ants_transform_sidecar-0.1.0.dist-info/METADATA
aind_ants_transform_sidecar-0.1.0.dist-info/WHEEL
aind_ants_transform_sidecar-0.1.0.dist-info/top_level.txt
aind_ants_transform_sidecar-0.1.0.dist-info/RECORD
