Metadata-Version: 2.4
Name: aind-ants-transform-sidecar
Version: 0.1.0
Summary: Metadata for ANTs transform objects
Author: Allen Institute for Neural Dynamics
Author-email: Galen Lynch <galen@galenlynch.com>
License-Expression: MIT
Project-URL: Repository, https://github.com/AllenNeuralDynamics/aind-ants-transform-sidecar/
Project-URL: Issues, https://github.com/AllenNeuralDynamics/aind-ants-transform-sidecar/issues
Project-URL: Changelog, https://github.com/AllenNeuralDynamics/aind-ants-transform-sidecar/blob/main/CHANGELOG.md
Classifier: Programming Language :: Python :: 3
Requires-Python: >=3.10
License-File: LICENSE
Requires-Dist: pydantic<3,>=2
Dynamic: license-file
